IRACCGateway/__init__.py
IRACCGateway/test.py
IRACCGateway/protocol/__init__.py
IRACCGateway/protocol/convert.py
IRACCGateway_python-0.0.12.dist-info/LICENSE
IRACCGateway_python-0.0.12.dist-info/METADATA
IRACCGateway_python-0.0.12.dist-info/WHEEL
IRACCGateway_python-0.0.12.dist-info/top_level.txt
IRACCGateway_python-0.0.12.dist-info/RECORD
