Metadata-Version: 2.1
Name: IRACCGateway-python
Version: 0.0.12
Summary: Driver for IRACCGateway(Daikin Specified Version)
Home-page: https://github.com/yangziy/IRACCGateway-python
Author: yangziy
Author-email: yangziy@outlook.com
License: UNKNOWN
Platform: UNKNOWN
Classifier: Programming Language :: Python :: 3
Classifier: License :: OSI Approved :: MIT License
Classifier: Operating System :: OS Independent
